entitygraph/__init__.py
entitygraph/admin.py
entitygraph/application.py
entitygraph/base_client.py
entitygraph/bulk_builder.py
entitygraph/entity.py
entitygraph/entity_builder.py
entitygraph/namespace_map.py
entitygraph/query.py
entitygraph/transaction.py
entitygraph_client-0.0.18.dist-info/METADATA
entitygraph_client-0.0.18.dist-info/WHEEL
entitygraph_client-0.0.18.dist-info/top_level.txt
entitygraph_client-0.0.18.dist-info/RECORD
