Metadata-Version: 2.1
Name: entitygraph-client
Version: 0.0.18
Summary: Python client for Maverick EntityGraph API
Author-email: Bechtle A/V Software Solutions 360° <patrick.maue@bechtle.com>
License: Apache 2.0
Keywords: Maverick,EntityGraph,API
Requires-Python: >=3.7
Requires-Dist: requests >=2.31.0
Requires-Dist: rdflib >=6.3.0
Requires-Dist: pandas >=2.0.3
